Workbook

Sheet Setup
A1: Print Rate Sheet — Setup
A2: Change these and every price on the Rate Sheet recalculates.
A4: HOW TO USE
A5: Yellow cells with blue text | B5: You fill these in. Nothing else should be edited.
A6: Black text | B6: Calculated. Leave alone.
A7: Rate Sheet tab | B7: Enter your wholesale cost per order. Prices appear automatically.
A8: Blank wholesale cost | B8: Row stays blank rather than showing a wrong number.
A11: YOUR NUMBERS
A12: Target gross margin | B12: 0.4
A13: Round prices up to nearest | B13: 5
A14: Minimum order value | B14: 75
A15: Rush uplift | B15: 0.25
A16: Design hourly rate | B16: 85
A17: Revision rounds included | B17: 1
A20: Starting values are placeholders chosen to be plausible, not advice — replace them with your own once you have run a few jobs.

Sheet Rate Sheet
A1: Print Rate Sheet
A2: Fill in column D only. Everything to the right calculates from Setup.
A4: Product | B4: Spec | C4: Qty | D4: Wholesale cost | E4: Cost / unit | F4: Price at target | G4: YOUR PRICE | H4: Margin $ | I4: Margin % | J4: Price / unit | K4: Above minimum? | L4: Key
A5: Business cards | B5: 3.5" x 2", 16pt matte | C5: 250 | D5: 26 | E5: =IF($D5="","",$D5/$C5) | F5: =IF($D5="","",IFERROR($D5/(1-Setup!$B$12),"")) | G5: =IF($F5="","",CEILING($F5,Setup!$B$13)) | H5: =IF($G5="","",$G5-$D5) | I5: =IF($G5="","",IFERROR($H5/$G5,"")) | J5: =IF($G5="","",$G5/$C5) | K5: =IF($G5="","",IF($G5>=Setup!$B$14,"Yes","BELOW MIN")) | L5: =$A5&"|"&$C5
A6: Business cards | B6: 3.5" x 2", 16pt matte | C6: 500 | E6: =IF($D6="","",$D6/$C6) | F6: =IF($D6="","",IFERROR($D6/(1-Setup!$B$12),"")) | G6: =IF($F6="","",CEILING($F6,Setup!$B$13)) | H6: =IF($G6="","",$G6-$D6) | I6: =IF($G6="","",IFERROR($H6/$G6,"")) | J6: =IF($G6="","",$G6/$C6) | K6: =IF($G6="","",IF($G6>=Setup!$B$14,"Yes","BELOW MIN")) | L6: =$A6&"|"&$C6
A7: Business cards | B7: 3.5" x 2", 16pt matte | C7: 1000 | E7: =IF($D7="","",$D7/$C7) | F7: =IF($D7="","",IFERROR($D7/(1-Setup!$B$12),"")) | G7: =IF($F7="","",CEILING($F7,Setup!$B$13)) | H7: =IF($G7="","",$G7-$D7) | I7: =IF($G7="","",IFERROR($H7/$G7,"")) | J7: =IF($G7="","",$G7/$C7) | K7: =IF($G7="","",IF($G7>=Setup!$B$14,"Yes","BELOW MIN")) | L7: =$A7&"|"&$C7
A8: Business cards | B8: 3.5" x 2", 16pt matte | C8: 2500 | E8: =IF($D8="","",$D8/$C8) | F8: =IF($D8="","",IFERROR($D8/(1-Setup!$B$12),"")) | G8: =IF($F8="","",CEILING($F8,Setup!$B$13)) | H8: =IF($G8="","",$G8-$D8) | I8: =IF($G8="","",IFERROR($H8/$G8,"")) | J8: =IF($G8="","",$G8/$C8) | K8: =IF($G8="","",IF($G8>=Setup!$B$14,"Yes","BELOW MIN")) | L8: =$A8&"|"&$C8
A9: Flyers | B9: 8.5" x 11", 100lb gloss | C9: 250 | E9: =IF($D9="","",$D9/$C9) | F9: =IF($D9="","",IFERROR($D9/(1-Setup!$B$12),"")) | G9: =IF($F9="","",CEILING($F9,Setup!$B$13)) | H9: =IF($G9="","",$G9-$D9) | I9: =IF($G9="","",IFERROR($H9/$G9,"")) | J9: =IF($G9="","",$G9/$C9) | K9: =IF($G9="","",IF($G9>=Setup!$B$14,"Yes","BELOW MIN")) | L9: =$A9&"|"&$C9
A10: Flyers | B10: 8.5" x 11", 100lb gloss | C10: 500 | E10: =IF($D10="","",$D10/$C10) | F10: =IF($D10="","",IFERROR($D10/(1-Setup!$B$12),"")) | G10: =IF($F10="","",CEILING($F10,Setup!$B$13)) | H10: =IF($G10="","",$G10-$D10) | I10: =IF($G10="","",IFERROR($H10/$G10,"")) | J10: =IF($G10="","",$G10/$C10) | K10: =IF($G10="","",IF($G10>=Setup!$B$14,"Yes","BELOW MIN")) | L10: =$A10&"|"&$C10
A11: Flyers | B11: 8.5" x 11", 100lb gloss | C11: 1000 | E11: =IF($D11="","",$D11/$C11) | F11: =IF($D11="","",IFERROR($D11/(1-Setup!$B$12),"")) | G11: =IF($F11="","",CEILING($F11,Setup!$B$13)) | H11: =IF($G11="","",$G11-$D11) | I11: =IF($G11="","",IFERROR($H11/$G11,"")) | J11: =IF($G11="","",$G11/$C11) | K11: =IF($G11="","",IF($G11>=Setup!$B$14,"Yes","BELOW MIN")) | L11: =$A11&"|"&$C11
A12: Flyers | B12: 8.5" x 11", 100lb gloss | C12: 2500 | E12: =IF($D12="","",$D12/$C12) | F12: =IF($D12="","",IFERROR($D12/(1-Setup!$B$12),"")) | G12: =IF($F12="","",CEILING($F12,Setup!$B$13)) | H12: =IF($G12="","",$G12-$D12) | I12: =IF($G12="","",IFERROR($H12/$G12,"")) | J12: =IF($G12="","",$G12/$C12) | K12: =IF($G12="","",IF($G12>=Setup!$B$14,"Yes","BELOW MIN")) | L12: =$A12&"|"&$C12
A13: Postcards (unmailed) | B13: 4" x 6", 16pt | C13: 250 | E13: =IF($D13="","",$D13/$C13) | F13: =IF($D13="","",IFERROR($D13/(1-Setup!$B$12),"")) | G13: =IF($F13="","",CEILING($F13,Setup!$B$13)) | H13: =IF($G13="","",$G13-$D13) | I13: =IF($G13="","",IFERROR($H13/$G13,"")) | J13: =IF($G13="","",$G13/$C13) | K13: =IF($G13="","",IF($G13>=Setup!$B$14,"Yes","BELOW MIN")) | L13: =$A13&"|"&$C13
A14: Postcards (unmailed) | B14: 4" x 6", 16pt | C14: 500 | E14: =IF($D14="","",$D14/$C14) | F14: =IF($D14="","",IFERROR($D14/(1-Setup!$B$12),"")) | G14: =IF($F14="","",CEILING($F14,Setup!$B$13)) | H14: =IF($G14="","",$G14-$D14) | I14: =IF($G14="","",IFERROR($H14/$G14,"")) | J14: =IF($G14="","",$G14/$C14) | K14: =IF($G14="","",IF($G14>=Setup!$B$14,"Yes","BELOW MIN")) | L14: =$A14&"|"&$C14
A15: Postcards (unmailed) | B15: 4" x 6", 16pt | C15: 1000 | E15: =IF($D15="","",$D15/$C15) | F15: =IF($D15="","",IFERROR($D15/(1-Setup!$B$12),"")) | G15: =IF($F15="","",CEILING($F15,Setup!$B$13)) | H15: =IF($G15="","",$G15-$D15) | I15: =IF($G15="","",IFERROR($H15/$G15,"")) | J15: =IF($G15="","",$G15/$C15) | K15: =IF($G15="","",IF($G15>=Setup!$B$14,"Yes","BELOW MIN")) | L15: =$A15&"|"&$C15
A16: Postcards (unmailed) | B16: 4" x 6", 16pt | C16: 2500 | E16: =IF($D16="","",$D16/$C16) | F16: =IF($D16="","",IFERROR($D16/(1-Setup!$B$12),"")) | G16: =IF($F16="","",CEILING($F16,Setup!$B$13)) | H16: =IF($G16="","",$G16-$D16) | I16: =IF($G16="","",IFERROR($H16/$G16,"")) | J16: =IF($G16="","",$G16/$C16) | K16: =IF($G16="","",IF($G16>=Setup!$B$14,"Yes","BELOW MIN")) | L16: =$A16&"|"&$C16
A17: Postcards (unmailed) | B17: 5" x 7", 16pt | C17: 500 | E17: =IF($D17="","",$D17/$C17) | F17: =IF($D17="","",IFERROR($D17/(1-Setup!$B$12),"")) | G17: =IF($F17="","",CEILING($F17,Setup!$B$13)) | H17: =IF($G17="","",$G17-$D17) | I17: =IF($G17="","",IFERROR($H17/$G17,"")) | J17: =IF($G17="","",$G17/$C17) | K17: =IF($G17="","",IF($G17>=Setup!$B$14,"Yes","BELOW MIN")) | L17: =$A17&"|"&$C17
... A27: Magnets (vehicle) | B27: 18" x 24", pair | C27: 1 | E27: =IF($D27="","",$D27/$C27) | F27: =IF($D27="","",IFERROR($D27/(1-Setup!$B$12),"")) | G27: =IF($F27="","",CEILING($F27,Setup!$B$13)) | H27: =IF($G27="","",$G27-$D27) | I27: =IF($G27="","",IFERROR($H27/$G27,"")) | J27: =IF($G27="","",$G27/$C27) | K27: =IF($G27="","",IF($G27>=Setup!$B$14,"Yes","BELOW MIN")) | L27: =$A27&"|"&$C27
A29: Wholesale costs are yours to supply — none are filled in except the example in D5. Specs are placeholders; change them to match what your printer actually quotes.

Sheet Design Fees
A1: Design Fees
A2: Print is cheap; design is not. Anything that is genuinely new artwork gets billed here rather than absorbed.
A4: Item | B4: Basis | C4: Rate | D4: Notes
A5: Postcard ad layout (mailing customers) | B5: Included | C5: 0 | D5: Already part of a mailing. Do not start charging for this.
A6: Reusing existing artwork on another product | B6: Included | C6: 0 | D6: Business cards or flyers from a design you already made. This is the whole advantage.
A7: New artwork from an existing brand | B7: Flat | C7: 150 | D7: Logo and colours exist; the layout does not.
A8: Brand-new design, no assets | B8: Hourly | C8: =Setup!$B$16 | D8: Uses the Setup hourly rate. Estimate hours before quoting.
A9: Brochure layout (tri-fold, 6 panels) | B9: Flat | C9: 350 | D9: The one that runs over. Quote separately, always.
A10: Vehicle magnet artwork | B10: Flat | C10: 125 | D10: Must be rebuilt for legibility at distance, not scaled down.
A11: Copywriting | B11: Hourly | C11: =Setup!$B$16 | D11: When the customer cannot supply wording. Common on flyers and brochures.
A12: Extra revision round | B12: Flat | C12: 45 | D12: Beyond the rounds included in the proof terms.
A13: Rush handling | B13: Uplift | C13: =Setup!$B$15 | D13: Setup rush uplift applied to the whole job, not just design.
A15: Flat rates are placeholders. They are set to be defensible rather than researched — replace them once you know how long each job really takes.

Sheet Quote Builder
A1: Quote Builder
A2: Type a product and quantity exactly as they appear on the Rate Sheet.
A4: Product | B4: Business cards
A5: Quantity | B5: 250
A7: Print price | B7: =IFERROR(INDEX('Rate Sheet'!$G$5:$G$27,MATCH($B$4&"|"&$B$5,'Rate Sheet'!$L$5:$L$27,0)),"Not on the rate sheet")
A8: Design fee (if any) | B8: 0
A9: Rush? | B9: No
A11: QUOTE TOTAL | B11: =IF(ISNUMBER($B$7),($B$7+$B$8)*IF($B$9="Yes",1+Setup!$B$15,1),"Check the product and quantity")
A13: Above minimum? | B13: =IF(ISNUMBER($B$11),IF($B$11>=Setup!$B$14,"Yes","Below minimum — roll into their next mailing invoice"),"")
A15: Rush applies the Setup uplift to the whole job. Design fees come from the Design Fees tab — enter the one that applies.
